db_by_josh/__init__.py
db_by_josh/query.py
db_by_josh/result.py
db_by_josh/schema.py
db_by_josh/sqlite3worker.py
db_by_josh/store.py
db_by_josh-0.0.3.dist-info/LICENSE.txt
db_by_josh-0.0.3.dist-info/METADATA
db_by_josh-0.0.3.dist-info/WHEEL
db_by_josh-0.0.3.dist-info/top_level.txt
db_by_josh-0.0.3.dist-info/RECORD
