Metadata-Version: 2.1
Name: db-by-josh
Version: 0.0.3
Summary: A thread safe DSL for sqlite3.
Home-page: https://github.com/josharnoldjosh/thread_safe_sqlite
Author: Josh Arnold
Author-email: dev@josharnold.me
License: MIT
Keywords: Sqlite3,Thread,Safe,DSL,Wrapper
Platform: UNKNOWN
Requires-Python: >=3.6
